CHANGES.txt
LICENSE.txt
MANIFEST.in
setup.py
Dfcapi.egg-info/PKG-INFO
Dfcapi.egg-info/SOURCES.txt
Dfcapi.egg-info/dependency_links.txt
Dfcapi.egg-info/requires.txt
Dfcapi.egg-info/top_level.txt
dfcapi/__init__.py