Metadata-Version: 1.0
Name: Dfcapi
Version: 1.0.0
Summary: DFC Hosted Web Services - Python Client Library
Home-page: https://github.com/dfcplc/dfcapi-python
Author: Debit Finance Collections Plc
Author-email: development@debitfinance.co.uk
License: LICENSE.txt
Platform: UNKNOWN
